Metadata-Version: 2.1
Name: django-multicurrency
Version: 0.1.2
Summary: Simple Django multicurrency field
Home-page: https://github.com/NeuralDynamicsWeb/django-multicurrency
Author: Neural Dynamics
Author-email: neuraldynamics.web@gmail.com
License: Apache 2.0
Download-URL: https://github.com/NeuralDynamicsWeb/django-multicurrency/archive/refs/tags/v_02.1.tar.gz
Keywords: Django,Multicurrency
Platform: UNKNOWN
Classifier: Development Status :: 5 - Production/Stable
Classifier: Environment :: Web Environment
Classifier: Framework :: Django
Classifier: Intended Audience :: Developers
Classifier: License :: OSI Approved :: Apache Software License
Classifier: Operating System :: OS Independent
Classifier: Programming Language :: Python
Classifier: Programming Language :: Python :: 3.6
Classifier: Programming Language :: Python :: 3.7
Classifier: Programming Language :: Python :: 3.8
Classifier: Framework :: Django
Classifier: Framework :: Django :: 3.0
Classifier: Framework :: Django :: 3.1
Classifier: Topic :: Internet :: WWW/HTTP
Classifier: Topic :: Internet :: WWW/HTTP :: Dynamic Content
Classifier: Topic :: Software Development :: Libraries :: Application Frameworks
Classifier: Topic :: Software Development :: Libraries :: Python Modules
Requires: Django (>=3.0)
Requires-Python: >=3.6
